[
    {
        "_id":"profile_gjh20oasodosh",
        "userId":"user01",
        "displayName":"UserProfile"
    },
    {
        "_id":"profile_ssppsdoaspds",
        "userId":"user02",
        "displayName":"UserProfile"
    },
    {
        "_id":"profile_lsksksslaxsla",
        "userId":"user03",
        "displayName":"UserProfile"
    },
    {
        "_id":"profile_iskklslkas",
        "userId":"user04",
        "displayName":"UserProfile"
    },
    {
        "_id":"profile_sasdkjhsdss",
        "userId":"user05",
        "displayName":"UserProfile"
    }
]